code_challenge/main.py
code_challenge-0.1.0.8.dist-info/entry_points.txt
code_challenge-0.1.0.8.dist-info/WHEEL
code_challenge-0.1.0.8.dist-info/METADATA
code_challenge-0.1.0.8.dist-info/RECORD
